{
  "timestamp": "2026-03-23T10:30:44.297587",
  "trade_type": "INTRADAY",
  "buy_count": 3,
  "sell_count": 3,
  "buy_signals": [
    {
      "symbol": "HCLTECH",
      "signal_type": "LONG_BUILDUP",
      "trade_type": "INTRADAY",
      "current_price": 1357.0,
      "price_change_pct": 1.75,
      "oi_change_pct": 8.79,
      "volume_spike": 1.67,
      "delivery_pct": null,
      "target": 1377.35,
      "stop_loss": 1346.14,
      "risk_reward": 1.87,
      "conviction_score": 86.2,
      "reasoning": "HCLTECH: Fresh long positions being built. Price +1.75% with OI +8.79%. BULLISH momentum. High volume confirms participation.",
      "timestamp": "2026-03-23 10:30:06 IST"
    },
    {
      "symbol": "M&M",
      "signal_type": "LONG_BUILDUP",
      "trade_type": "INTRADAY",
      "current_price": 2948.0,
      "price_change_pct": 1.35,
      "oi_change_pct": 7.12,
      "volume_spike": 1.67,
      "delivery_pct": null,
      "target": 2992.22,
      "stop_loss": 2924.42,
      "risk_reward": 1.88,
      "conviction_score": 74.7,
      "reasoning": "M&M: Fresh long positions being built. Price +1.35% with OI +7.12%. BULLISH momentum. High volume confirms participation.",
      "timestamp": "2026-03-23 10:30:12 IST"
    },
    {
      "symbol": "POWERGRID",
      "signal_type": "LONG_BUILDUP",
      "trade_type": "INTRADAY",
      "current_price": 300.0,
      "price_change_pct": 0.81,
      "oi_change_pct": 7.7,
      "volume_spike": 1.67,
      "delivery_pct": null,
      "target": 304.5,
      "stop_loss": 297.6,
      "risk_reward": 1.87,
      "conviction_score": 65.5,
      "reasoning": "POWERGRID: Fresh long positions being built. Price +0.81% with OI +7.70%. BULLISH momentum. High volume confirms participation.",
      "timestamp": "2026-03-23 10:30:07 IST"
    }
  ],
  "sell_signals": [
    {
      "symbol": "ADANIENSOL",
      "signal_type": "SHORT_BUILDUP",
      "trade_type": "INTRADAY",
      "current_price": 944.0,
      "price_change_pct": -6.47,
      "oi_change_pct": 16.29,
      "volume_spike": 1.67,
      "delivery_pct": null,
      "target": 929.84,
      "stop_loss": 951.55,
      "risk_reward": 1.87,
      "conviction_score": 95.0,
      "reasoning": "ADANIENSOL: Fresh short positions being built. Price -6.47% with OI +16.29%. BEARISH momentum. High volume confirms participation.",
      "timestamp": "2026-03-23 10:30:04 IST"
    },
    {
      "symbol": "LODHA",
      "signal_type": "SHORT_BUILDUP",
      "trade_type": "INTRADAY",
      "current_price": 726.0,
      "price_change_pct": -8.9,
      "oi_change_pct": 14.86,
      "volume_spike": 1.67,
      "delivery_pct": null,
      "target": 715.11,
      "stop_loss": 731.81,
      "risk_reward": 1.88,
      "conviction_score": 95.0,
      "reasoning": "LODHA: Fresh short positions being built. Price -8.90% with OI +14.86%. BEARISH momentum. High volume confirms participation.",
      "timestamp": "2026-03-23 10:30:05 IST"
    },
    {
      "symbol": "360ONE",
      "signal_type": "SHORT_BUILDUP",
      "trade_type": "INTRADAY",
      "current_price": 982.0,
      "price_change_pct": -5.61,
      "oi_change_pct": 14.43,
      "volume_spike": 1.67,
      "delivery_pct": null,
      "target": 967.27,
      "stop_loss": 989.86,
      "risk_reward": 1.88,
      "conviction_score": 95.0,
      "reasoning": "360ONE: Fresh short positions being built. Price -5.61% with OI +14.43%. BEARISH momentum. High volume confirms participation.",
      "timestamp": "2026-03-23 10:30:05 IST"
    }
  ]
}