{
  "timestamp": "2026-04-07T16:00:29.658071+05:30",
  "trade_type": "INTRADAY",
  "buy_count": 3,
  "sell_count": 4,
  "buy_signals": [
    {
      "symbol": "GODREJCP",
      "signal_type": "LONG_BUILDUP",
      "trade_type": "INTRADAY",
      "current_price": 1026.15,
      "price_change_pct": 2.42,
      "oi_change_pct": 12.69,
      "volume_spike": 4.44,
      "delivery_pct": 39.8,
      "target": 1048.88,
      "stop_loss": 1015.89,
      "risk_reward": 2.22,
      "conviction_score": 88.0,
      "reasoning": "Long buildup confirmed. Price +2.42% | OI +12.69% | 4.4\u00d7 vol | Delivery 40% | Nifty bullish | VWAP \u20b91025.85 (\u2705 aligned). BULLISH setup.",
      "timestamp": "2026-04-07 16:00 IST",
      "vwap": 1025.85,
      "vwap_aligned": true,
      "entry_quality": "MODERATE",
      "session_context": "BTST",
      "is_repeat": false,
      "repeat_days": 0,
      "ce_pe_bias": "N/A",
      "pcr": 0.0,
      "ce_oi_change": 0.0,
      "pe_oi_change": 0.0,
      "options_aligned": false,
      "max_pain": null
    },
    {
      "symbol": "HYUNDAI",
      "signal_type": "LONG_BUILDUP",
      "trade_type": "INTRADAY",
      "current_price": 1710.4,
      "price_change_pct": 1.12,
      "oi_change_pct": 11.35,
      "volume_spike": 1.92,
      "delivery_pct": 72.4,
      "target": 1746.46,
      "stop_loss": 1696.72,
      "risk_reward": 2.64,
      "conviction_score": 86.6,
      "reasoning": "Long buildup confirmed. Price +1.12% | OI +11.35% | 1.9\u00d7 vol | Delivery 72% | Nifty bullish | VWAP \u20b91694.47 (\u2705 aligned). BULLISH setup.",
      "timestamp": "2026-04-07 16:00 IST",
      "vwap": 1694.47,
      "vwap_aligned": true,
      "entry_quality": "FRESH",
      "session_context": "BTST",
      "is_repeat": false,
      "repeat_days": 0,
      "ce_pe_bias": "N/A",
      "pcr": 0.0,
      "ce_oi_change": 0.0,
      "pe_oi_change": 0.0,
      "options_aligned": false,
      "max_pain": null
    },
    {
      "symbol": "KPITTECH",
      "signal_type": "LONG_BUILDUP",
      "trade_type": "INTRADAY",
      "current_price": 709.75,
      "price_change_pct": 2.14,
      "oi_change_pct": 10.84,
      "volume_spike": 1.5,
      "delivery_pct": 35.4,
      "target": 724.42,
      "stop_loss": 702.65,
      "risk_reward": 2.07,
      "conviction_score": 75.7,
      "reasoning": "Long buildup confirmed. Price +2.14% | OI +10.84% | 1.5\u00d7 vol | Delivery 35% | Nifty bullish | VWAP \u20b9700.49 (\u2705 aligned). BULLISH setup.",
      "timestamp": "2026-04-07 16:00 IST",
      "vwap": 700.49,
      "vwap_aligned": true,
      "entry_quality": "MODERATE",
      "session_context": "BTST",
      "is_repeat": false,
      "repeat_days": 0,
      "ce_pe_bias": "N/A",
      "pcr": 0.0,
      "ce_oi_change": 0.0,
      "pe_oi_change": 0.0,
      "options_aligned": false,
      "max_pain": null
    }
  ],
  "sell_signals": [
    {
      "symbol": "VMM",
      "signal_type": "SHORT_BUILDUP",
      "trade_type": "INTRADAY",
      "current_price": 112.0,
      "price_change_pct": -1.53,
      "oi_change_pct": 13.5,
      "volume_spike": 2.93,
      "delivery_pct": 48.4,
      "target": 109.45,
      "stop_loss": 113.01,
      "risk_reward": 2.53,
      "conviction_score": 76.8,
      "reasoning": "Short buildup confirmed. Price -1.53% | OI +13.50% | 2.9\u00d7 vol | Delivery 48% | Nifty bullish | VWAP \u20b9113.18 (\u2705 aligned). BEARISH setup.",
      "timestamp": "2026-04-07 16:00 IST",
      "vwap": 113.18,
      "vwap_aligned": true,
      "entry_quality": "MODERATE",
      "session_context": "BTST",
      "is_repeat": false,
      "repeat_days": 0,
      "ce_pe_bias": "N/A",
      "pcr": 0.0,
      "ce_oi_change": 0.0,
      "pe_oi_change": 0.0,
      "options_aligned": false,
      "max_pain": null
    },
    {
      "symbol": "JUBLFOOD",
      "signal_type": "SHORT_BUILDUP",
      "trade_type": "INTRADAY",
      "current_price": 412.75,
      "price_change_pct": -10.49,
      "oi_change_pct": 76.48,
      "volume_spike": 7.91,
      "delivery_pct": 25.7,
      "target": 402.84,
      "stop_loss": 417.7,
      "risk_reward": 2.0,
      "conviction_score": 73.0,
      "reasoning": "Short buildup confirmed. Price -10.49% | OI +76.48% | 7.9\u00d7 vol | Delivery 26% | Nifty bullish | VWAP \u20b9420.41 (\u2705 aligned). BEARISH setup.",
      "timestamp": "2026-04-07 16:00 IST",
      "vwap": 420.41,
      "vwap_aligned": true,
      "entry_quality": "EXTENDED",
      "session_context": "BTST",
      "is_repeat": false,
      "repeat_days": 0,
      "ce_pe_bias": "N/A",
      "pcr": 0.0,
      "ce_oi_change": 0.0,
      "pe_oi_change": 0.0,
      "options_aligned": false,
      "max_pain": null
    },
    {
      "symbol": "BIOCON",
      "signal_type": "SHORT_BUILDUP",
      "trade_type": "INTRADAY",
      "current_price": 340.25,
      "price_change_pct": -4.15,
      "oi_change_pct": 23.92,
      "volume_spike": 4.82,
      "delivery_pct": 36.7,
      "target": 332.08,
      "stop_loss": 344.33,
      "risk_reward": 2.0,
      "conviction_score": 73.0,
      "reasoning": "Short buildup confirmed. Price -4.15% | OI +23.92% | 4.8\u00d7 vol | Delivery 37% | Nifty bullish | VWAP \u20b9345.58 (\u2705 aligned). BEARISH setup.",
      "timestamp": "2026-04-07 16:00 IST",
      "vwap": 345.58,
      "vwap_aligned": true,
      "entry_quality": "EXTENDED",
      "session_context": "BTST",
      "is_repeat": false,
      "repeat_days": 0,
      "ce_pe_bias": "N/A",
      "pcr": 0.0,
      "ce_oi_change": 0.0,
      "pe_oi_change": 0.0,
      "options_aligned": false,
      "max_pain": null
    },
    {
      "symbol": "BANKINDIA",
      "signal_type": "SHORT_BUILDUP",
      "trade_type": "INTRADAY",
      "current_price": 137.5,
      "price_change_pct": -3.88,
      "oi_change_pct": 18.03,
      "volume_spike": 5.79,
      "delivery_pct": 39.9,
      "target": 134.2,
      "stop_loss": 139.15,
      "risk_reward": 2.0,
      "conviction_score": 73.0,
      "reasoning": "Short buildup confirmed. Price -3.88% | OI +18.03% | 5.8\u00d7 vol | Delivery 40% | Nifty bullish | VWAP \u20b9137.65 (\u2705 aligned). BEARISH setup.",
      "timestamp": "2026-04-07 16:00 IST",
      "vwap": 137.65,
      "vwap_aligned": true,
      "entry_quality": "EXTENDED",
      "session_context": "BTST",
      "is_repeat": false,
      "repeat_days": 0,
      "ce_pe_bias": "N/A",
      "pcr": 0.0,
      "ce_oi_change": 0.0,
      "pe_oi_change": 0.0,
      "options_aligned": false,
      "max_pain": null
    }
  ]
}